prasopes/__init__.py
prasopes/__main__.py
prasopes/config.py
prasopes/datasets.py
prasopes/datasets_oldbak.py
prasopes/datatools.py
prasopes/datatools_bak.py
prasopes/docks.py
prasopes/drlmobtools_gui.py
prasopes/drltools.py
prasopes/drltools_gui.py
prasopes/filetools.py
prasopes/graphtools.py
prasopes/imagetools.py
prasopes/imagetools_dirtywip.py
prasopes/mobtools.py
prasopes/mobtools_gui.py
prasopes/msonmobtools.py
prasopes/msonmobtools_gui.py
prasopes/predictmz.py
prasopes/reactivitytools.py
prasopes/tangoicons.py
prasopes/testbris.py
prasopes/testints.py
prasopes/testung_oldbak.py
prasopes/testungraw.py
prasopes/toftools.py
prasopes/zcetools.py
prasopes/zcetools_help.py
prasopes-0.0.56.dist-info/METADATA
prasopes-0.0.56.dist-info/WHEEL
prasopes-0.0.56.dist-info/entry_points.txt
prasopes-0.0.56.dist-info/top_level.txt
prasopes-0.0.56.dist-info/RECORD
