Metadata-Version: 2.1
Name: prasopes
Version: 0.0.56
Summary: Thermo/Finnigan .raw file viewer based on rawprasslib
Home-page: https://gitlab.science.ru.nl/jzelenka/prasopes
Author: Jan Zelenka
Author-email: 3yanyanyan@gmail.com
License: UNKNOWN
Platform: UNKNOWN
Classifier: Programming Language :: Python
Classifier: Programming Language :: Python :: 3
Classifier: Programming Language :: Python :: 3.5
Classifier: Programming Language :: Python :: 3.6
Classifier: Programming Language :: Python :: 3.7
Classifier: Operating System :: OS Independent
Classifier: Operating System :: Microsoft :: Windows
Classifier: Operating System :: Unix
Classifier: Operating System :: MacOS
Classifier: Development Status :: 3 - Alpha
Classifier: Intended Audience :: Science/Research
Classifier: Topic :: Scientific/Engineering :: Chemistry
Requires-Python: >=3.5
Requires-Dist: numpy (>=1.13.0)
Requires-Dist: matplotlib (>=3.0.0)
Requires-Dist: rawprasslib (>=0.0.6)
Requires-Dist: opentims-bruker-bridge
Requires-Dist: opentimspy
Requires-Dist: PyQt5 ; platform_system == "Darwin"
Requires-Dist: PyQt5-sip ; platform_system == "Darwin"
Requires-Dist: PyQt5 ; platform_system == "Windows"
Requires-Dist: PyQt5-sip ; platform_system == "Windows"
Provides-Extra: raw_parameters_readout
Requires-Dist: rawautoparams (>=0.0.3) ; extra == 'raw_parameters_readout'
